LICENSE
MANIFEST.in
README.md
RELEASE-VERSION
setup.py
version.py
stakesign/__init__.py
stakesign/__main__.py
stakesign/docker.py
stakesign/git.py
stakesign/prepare.py
stakesign/verify.py
stakesign.egg-info/PKG-INFO
stakesign.egg-info/SOURCES.txt
stakesign.egg-info/dependency_links.txt
stakesign.egg-info/entry_points.txt
stakesign.egg-info/requires.txt
stakesign.egg-info/top_level.txt