Metadata-Version: 2.1
Name: stakesign
Version: 0.2.1
Summary: Sign files via blockchain + put your money where your mouth is
Home-page: https://github.com/mlin/stakesign
Author: Mike Lin
Author-email: dna@mlin.net
License: MIT
Platform: UNKNOWN
Requires-Python: >=3.6
